async_class.py
async_class-0.5.0.dist-info/LICENSE
async_class-0.5.0.dist-info/METADATA
async_class-0.5.0.dist-info/WHEEL
async_class-0.5.0.dist-info/top_level.txt
async_class-0.5.0.dist-info/RECORD
